Workbook

Sheet Hướng dẫn
A1: Kho kinh nghiệm lỗi của Lotus POS. Mỗi lỗi phát hiện hoặc sửa (kể cả do AI khác sửa) thêm MỘT dòng vào sheet Bug List.
A2: ID: PT-xx (Phát Tài), ECHO-xx, SAAS-xx (repo lotus-pos-saas), theo thứ tự tăng dần.
A3: Nguồn / Mức độ / Trạng thái: chọn từ danh sách thả xuống. Cao = hỏng chức năng thật; Trung = mất dữ liệu nhập, sai trạng thái; Thấp = giao diện.
A4: Nguyên nhân gốc: ghi cơ chế kỹ thuật (API, giới hạn, dòng code), không ghi "do sơ suất".
A5: Test chặn tái phạm: tên file test hoặc "—" nếu chưa có (khi đó ghi lý do ở cột Bài học).
A6: Bài học / câu hỏi rà soát: câu hỏi để tìm lỗi cùng loại ở chỗ khác. Hạng mục lặp lại nhiều lần thì thêm vào sheet Checklist rà soát.
A7: Commit / tham chiếu: hash commit (pos-phattai cho dòng PT-, lotus-pos-saas cho dòng SAAS-/ECHO-) hoặc phiên bản sản phẩm cũ. Một bản sửa đã đẩy lên luôn có hash.
A8: Sheet Thống kê tự đếm bằng công thức; không sửa tay.

Sheet Bug List
A1: ID | B1: Ngày phát hiện | C1: Nguồn | D1: Phân hệ | E1: File / vị trí | F1: Môi trường lộ lỗi | G1: Mức độ | H1: Nhóm lỗi | I1: Triệu chứng | J1: Nguyên nhân gốc (kỹ thuật) | K1: Cách sửa | L1: Test chặn tái phạm | M1: Bài học / câu hỏi rà soát | N1: Commit / tham chiếu | O1: Trạng thái
A2: PT-01 | B2: 2026-10-02 | C2: Phát Tài | D2: Staff UI | E2: public/staff/staff.js message() | F2: Mọi máy | G2: Trung | H2: Render mất dữ liệu | I2: Đang gõ SĐT hội viên/voucher/ghi chú, vài giây sau ô nhập trống; tra cứu báo 400. E2E chập chờn. | J2: Timer 7 giây của thông báo gọi render() toàn trang → dựng lại DOM, mất giá trị input chưa lưu vào state. Tái hiện bằng PRE_WAIT=7000. | K2: message() chỉ gỡ phần tử thông báo, không render lại. | L2: tests/phattai-v174-build-strip.test.mjs: "FLAKE a fading notice removes only the notice: it must not re-render and wipe typed fields"; scripts/e2e-staff.mjs gõ SĐT rồi chờ quá 7 s. | M2: Mọi setTimeout/sự kiện nền gọi render toàn trang? Mọi input có oninput lưu vào state? | N2: d95ccd2 | O2: Đã sửa
A3: PT-02 | B3: 2026-10-02 | C3: Phát Tài | D3: Staff UI / In | E3: public/staff/staff.js notify() | F3: Máy quầy có máy in | G3: Trung | H3: Render mất dữ liệu | I3: Thu ngân đang gõ thì báo cáo in xong làm ô nhập bị xóa. | J3: Cùng gốc PT-01: callback báo cáo in gọi message()/render đầy đủ. | K3: notify() thay nội dung thông báo tại chỗ, không render. | L3: tests/phattai-v176-update-resume.test.mjs: "KITCHEN printer reports only swap the notice; they never re-render over a form being typed". | M3: Callback từ native/WebSocket/polling chỉ cập nhật cục bộ. | N3: 014fd22 | O3: Đã sửa
A4: PT-03 | B4: 2026-10-02 | C4: Phát Tài | D4: Web QR / Staff | E4: public/assets/app.js, staff.js, display.js, counter/devices.js | F4: iOS 15, WebView cũ | G4: Cao | H4: Engine cũ | I4: Trang QR trắng/lỗi mạng trên iPhone iOS 15 và WebView cũ. | J4: AbortSignal.timeout() (Chrome 103 / iOS 16) không tồn tại → TypeError trước khi fetch. | K4: Hàm timeoutSignal(ms) dùng AbortController + setTimeout khi thiếu AbortSignal.timeout, áp ở cả 4 file. | L4: tests/phattai-v175-old-devices.test.mjs: "OLD DEVICES requests still time out where AbortSignal.timeout is missing"; scripts/e2e-staff.mjs xóa AbortSignal.timeout trên máy cầm tay và điện thoại khách. | M4: Quét API mới không có fallback: AbortSignal.timeout, replaceAll, Object.hasOwn, Array.at, findLast, structuredClone, crypto.randomUUID, ??=. | N4: b053657 | O4: Đã sửa
A5: PT-04 | B5: 2026-10-02 | C5: Phát Tài | D5: Staff / Báo cáo | E5: public/staff/staff.js xuất CSV | F5: SUNMI WebView Chromium 83 | G5: Cao | H5: Engine cũ | I5: Xuất CSV lỗi trên máy SUNMI. | J5: String.prototype.replaceAll chỉ có từ Chrome 85. | K5: Dùng .replace(/"/g,'""'). | L5: tests/phattai-v175-old-devices.test.mjs: "OLD DEVICES no unguarded browser API that Chromium 83 or iOS 15 lacks"; scripts/e2e-staff.mjs xóa String.replaceAll. | M5: Như PT-03. | N5: b053657 | O5: Đã sửa
A6: PT-05 | B6: 2026-10-02 | C6: Phát Tài | D6: CSS | E6: public/assets/app.css | F6: iOS cũ | G6: Thấp | H6: Engine cũ | I6: Bố cục QR vỡ trên iOS cũ. | J6: Đơn vị dvh không có fallback vh; thuộc tính rút gọn inset không có trên iOS < 14.5. | K6: Khai báo vh trước dvh; thay inset bằng top/right/bottom/left. | L6: tests/phattai-v175-old-devices.test.mjs: "OLD DEVICES the customer page keeps a vh fallback wherever it uses dvh (iOS < 15.4)" và "no unguarded browser API…" (inset). | M6: Rà dvh/svh, inset, gap trong flex, aspect-ratio, :has(), :is() thiếu fallback. | N6: b053657 | O6: Đã sửa
A7: PT-06 | B7: 2026-10-02 | C7: Phát Tài | D7: Worker / Realtime | E7: src/worker.js /api/realtime | F7: SUNMI V2s WebView Chromium 83 (Android 11) | G7: Cao | H7: Khác biệt WebView | I7: Máy cầm tay không nhận đơn mới tức thì, âm thầm quay về polling, không báo lỗi. | J7: Worker kiểm Origin của WebSocket và chỉ chấp nhận "null"; WebView gốc SUNMI (Chromium 83) gửi "file://" khi trang nạp từ file://. Chỉ lộ trên emulator/thiết bị Android 11 thật. | K7: Chấp nhận cả "null" và "file://" (vẫn bắt buộc bearer session trong subprotocol), log Origin bị từ chối. | L7: tests/phattai-v162-optimization.test.mjs: "REALTIME the packaged SUNMI app may connect from file:// whether its WebView says null or file://"; .github/workflows/apk-device.yml (emulator Android 11). | M7: Mọi whitelist Origin/Referer/CORS phải tính WebView; mọi fallback im lặng phải log + hiện trạng thái RT trên thanh chẩn đoán. | N7: e26fee4 | O7: Đã sửa
A8: PT-07 | B8: 2026-10-02 | C8: Phát Tài | D8: Android / Cập nhật | E8: android/.../AppUpdater.java | F8: Android 11 khi cấp quyền cài từ nguồn không rõ | G8: Cao | H8: Trạng thái trong bộ nhớ | I8: Bấm cập nhật → sang màn cấp quyền → cấp xong app bị tắt, cập nhật không tiếp tục. | J8: Android kill process khi quyền REQUEST_INSTALL_PACKAGES thay đổi; trạng thái "đang cập nhật" chỉ nằm trong RAM. | K8: Lưu resume_until (10 phút) vào SharedPreferences; onResume tự tiếp tục requestInstallUpdate. | L8: tests/phattai-v176-update-resume.test.mjs: "UPDATE the started update is remembered before Android settings open", "UPDATE after the restart the update resumes only if allowed, recent, and still available"; tests/UpdatePolicyHarness.java. | M8: Luồng nào phụ thuộc RAM mà có bước hệ thống kill app (quyền, đổi ngôn ngữ, xoay màn hình)? App Android mới của SaaS phải giữ cơ chế này. | N8: ed7b53a | O8: Đã sửa
A9: PT-08 | B9: 2026-10-02 | C9: Phát Tài | D9: Staff UI / Thanh toán | E9: public/staff/staff.js onNativeEvent → open() | F9: Emulator/thiết bị có sự kiện native | G9: Cao | H9: Render mất trạng thái | I9: Đang ở bước thanh toán, máy in bếp báo xong → màn hình nhảy về chi tiết đơn, mất bước thanh toán. | J9: onNativeEvent gọi open() vốn reset st.payFlow và st.screen. | K9: reloadDetail() tải lại dữ liệu nhưng giữ payFlow. | L9: tests/phattai-v176-update-resume.test.mjs: "KITCHEN a print report refreshes the order without leaving the payment step"; scripts/e2e-staff.mjs mock cầu native báo KITCHEN_SENT sau mỗi lệnh in. | M9: Hàm "mở" gọi từ sự kiện nền có reset luồng đang chạy không? | N9: 707ddb1 | O9: Đã sửa
A10: PT-09 | B10: 2026-10-02 | C10: Phát Tài | D10: Staff UI / Đơn | E10: public/staff/staff.js detail() | F10: Mọi máy | G10: Cao | H10: Payload một phần | I10: Treo/lỗi "Cannot read property 'filter' of undefined" ngay sau Chốt đơn. | J10: POST tạo đơn trả {order} trần, không có bills/jobs; detail() giả định payload GET đầy đủ. | K10: detail() kiểm thiếu mảng → hiện "Đang tải đơn…" rồi GET bản đầy đủ. | L10: tests/phattai-v176-update-resume.test.mjs: “KITCHEN a just-created order shows "loading" instead of crashing the render”. | M10: Mọi chỗ render lấy mảng từ API mà không || []; phản hồi POST/PUT khác GET. | N10: 707ddb1 | O10: Đã sửa
A11: PT-10 | B11: 2026-10-02 | C11: Phát Tài | D11: CSS | E11: staff.css #diag | F11: Mọi máy | G11: Thấp | H11: CSS | I11: Chữ cảnh báo trên thanh trạng thái khó đọc. | J11: Dùng lớp .warn chung (thiết kế cho hộp nền sáng) trên nền tối. | K11: Lớp riêng #diag.diag-warn{color:#ffd9a0}. | L11: tests/phattai-v174-build-strip.test.mjs: "STRIP the staff warning colour is its own class: the generic .warn box made it unreadable on the device". | M11: Lớp CSS dùng chung cho nhiều màu nền. | N11: e26fee4 | O11: Đã sửa
A12: PT-11 | B12: 2026-10-02 | C12: Phát Tài | D12: CSS / QR | E12: app.css thanh phiên bản | F12: Mọi máy | G12: Thấp | H12: CSS | I12: Thanh phiên bản trang QR không dính khi cuộn. | J12: position:sticky vô hiệu khi html/body có overflow-x:hidden. | K12: position:fixed + margin-top cho .app. | L12: tests/phattai-v174-build-strip.test.mjs: "STRIP the customer page pins the strip to the top and moves the app below it". | M12: sticky trong cha có overflow khác visible. | N12: 3456ad2 (bắt được trước khi phát hành) | O12: Đã sửa
... A82: SAAS-32 | B82: 2026-10-03 | C82: Phát Tài | D82: In / Biên lai | E82: public/counter/devices.js; public/staff/staff.js printBrowserReceipt/printReceipt; android MainActivity, TicketBitmap | F82: Mọi đường in biên lai | G82: Trung | H82: Nghiệp vụ / pháp lý | I82: Phiếu sau thanh toán ghi "HÓA ĐƠN THANH TOÁN", "Mã HĐ" (quầy) hoặc "HÓA ĐƠN / 收款小票" (SUNMI LAN) dù hệ thống không phát hành hóa đơn điện tử; không ghi ai thu tiền. Hai nút in trình duyệt cho hai bố cục khác nhau (một có địa chỉ/MST, một không). | J82: Mỗi đường in tự viết tiêu đề cứng và trôi khỏi nhau; dữ liệu đơn không lưu người xác nhận thanh toán nên không in được người thu. | K82: Payload biên lai mang tiêu đề, câu "Không phải hóa đơn", người thu, giờ thu, lời cảm ơn; mọi đường in đọc từ payload (APK cũ vẫn có giá trị dự phòng). Migration 0005 lưu paid_by/paid_by_name lúc thu cho đơn và bill. Một hàm browserReceipt() cho cả hai nút in. | L82: tests/receipt.test.mjs: người thu lưu khi trả đơn và bill, giữ nguyên sau khi đổi tên; mọi đường in có tiêu đề biên lai, không còn "HÓA ĐƠN". | M82: Chữ trên giấy in là cam kết với khách và thuế: đặt ở một nơi (payload), các máy in chỉ trình bày. | N82: 3f4e431 (lotus-pos-saas, R1) | O82: Đã sửa

Sheet Thống kê
A1: Nhóm lỗi | B1: Cao | C1: Trung | D1: Thấp | E1: Tổng
A2: Async | B2: =COUNTIFS('Bug List'!$H:$H,$A2,'Bug List'!$G:$G,"Cao") -> 0 | C2: =COUNTIFS('Bug List'!$H:$H,$A2,'Bug List'!$G:$G,"Trung") -> 1 | D2: =COUNTIFS('Bug List'!$H:$H,$A2,'Bug List'!$G:$G,"Thấp") -> 1 | E2: =SUM(B2:D2) -> 2
A3: CSS | B3: =COUNTIFS('Bug List'!$H:$H,$A3,'Bug List'!$G:$G,"Cao") -> 0 | C3: =COUNTIFS('Bug List'!$H:$H,$A3,'Bug List'!$G:$G,"Trung") -> 0 | D3: =COUNTIFS('Bug List'!$H:$H,$A3,'Bug List'!$G:$G,"Thấp") -> 3 | E3: =SUM(B3:D3) -> 3
A4: Cách ly quán | B4: =COUNTIFS('Bug List'!$H:$H,$A4,'Bug List'!$G:$G,"Cao") -> 4 | C4: =COUNTIFS('Bug List'!$H:$H,$A4,'Bug List'!$G:$G,"Trung") -> 1 | D4: =COUNTIFS('Bug List'!$H:$H,$A4,'Bug List'!$G:$G,"Thấp") -> 0 | E4: =SUM(B4:D4) -> 5
A5: Cấu hình | B5: =COUNTIFS('Bug List'!$H:$H,$A5,'Bug List'!$G:$G,"Cao") -> 0 | C5: =COUNTIFS('Bug List'!$H:$H,$A5,'Bug List'!$G:$G,"Trung") -> 0 | D5: =COUNTIFS('Bug List'!$H:$H,$A5,'Bug List'!$G:$G,"Thấp") -> 1 | E5: =SUM(B5:D5) -> 1
A6: Cờ tính năng | B6: =COUNTIFS('Bug List'!$H:$H,$A6,'Bug List'!$G:$G,"Cao") -> 0 | C6: =COUNTIFS('Bug List'!$H:$H,$A6,'Bug List'!$G:$G,"Trung") -> 1 | D6: =COUNTIFS('Bug List'!$H:$H,$A6,'Bug List'!$G:$G,"Thấp") -> 0 | E6: =SUM(B6:D6) -> 1
A7: Dữ liệu quán trong code | B7: =COUNTIFS('Bug List'!$H:$H,$A7,'Bug List'!$G:$G,"Cao") -> 1 | C7: =COUNTIFS('Bug List'!$H:$H,$A7,'Bug List'!$G:$G,"Trung") -> 0 | D7: =COUNTIFS('Bug List'!$H:$H,$A7,'Bug List'!$G:$G,"Thấp") -> 1 | E7: =SUM(B7:D7) -> 2
A8: Engine cũ | B8: =COUNTIFS('Bug List'!$H:$H,$A8,'Bug List'!$G:$G,"Cao") -> 2 | C8: =COUNTIFS('Bug List'!$H:$H,$A8,'Bug List'!$G:$G,"Trung") -> 0 | D8: =COUNTIFS('Bug List'!$H:$H,$A8,'Bug List'!$G:$G,"Thấp") -> 2 | E8: =SUM(B8:D8) -> 4
A9: Event delegation | B9: =COUNTIFS('Bug List'!$H:$H,$A9,'Bug List'!$G:$G,"Cao") -> 0 | C9: =COUNTIFS('Bug List'!$H:$H,$A9,'Bug List'!$G:$G,"Trung") -> 1 | D9: =COUNTIFS('Bug List'!$H:$H,$A9,'Bug List'!$G:$G,"Thấp") -> 0 | E9: =SUM(B9:D9) -> 1
A10: Fork theo khách | B10: =COUNTIFS('Bug List'!$H:$H,$A10,'Bug List'!$G:$G,"Cao") -> 2 | C10: =COUNTIFS('Bug List'!$H:$H,$A10,'Bug List'!$G:$G,"Trung") -> 1 | D10: =COUNTIFS('Bug List'!$H:$H,$A10,'Bug List'!$G:$G,"Thấp") -> 1 | E10: =SUM(B10:D10) -> 4
A11: Giao diện | B11: =COUNTIFS('Bug List'!$H:$H,$A11,'Bug List'!$G:$G,"Cao") -> 0 | C11: =COUNTIFS('Bug List'!$H:$H,$A11,'Bug List'!$G:$G,"Trung") -> 3 | D11: =COUNTIFS('Bug List'!$H:$H,$A11,'Bug List'!$G:$G,"Thấp") -> 2 | E11: =SUM(B11:D11) -> 5
A12: Giao diện / DOM | B12: =COUNTIFS('Bug List'!$H:$H,$A12,'Bug List'!$G:$G,"Cao") -> 2 | C12: =COUNTIFS('Bug List'!$H:$H,$A12,'Bug List'!$G:$G,"Trung") -> 0 | D12: =COUNTIFS('Bug List'!$H:$H,$A12,'Bug List'!$G:$G,"Thấp") -> 0 | E12: =SUM(B12:D12) -> 2
A13: Giao diện / sự kiện | B13: =COUNTIFS('Bug List'!$H:$H,$A13,'Bug List'!$G:$G,"Cao") -> 1 | C13: =COUNTIFS('Bug List'!$H:$H,$A13,'Bug List'!$G:$G,"Trung") -> 0 | D13: =COUNTIFS('Bug List'!$H:$H,$A13,'Bug List'!$G:$G,"Thấp") -> 0 | E13: =SUM(B13:D13) -> 1
... A39: Đồng bộ / giao diện | B39: =COUNTIFS('Bug List'!$H:$H,$A39,'Bug List'!$G:$G,"Cao") -> 0 | C39: =COUNTIFS('Bug List'!$H:$H,$A39,'Bug List'!$G:$G,"Trung") -> 2 | D39: =COUNTIFS('Bug List'!$H:$H,$A39,'Bug List'!$G:$G,"Thấp") -> 0 | E39: =SUM(B39:D39) -> 2
A40: Tổng | B40: =SUM(B2:B39) -> 24 | C40: =SUM(C2:C39) -> 36 | D40: =SUM(D2:D39) -> 21 | E40: =SUM(E2:E39) -> 81
A42: Trạng thái | B42: Số lỗi
A43: Mới | B43: =COUNTIF('Bug List'!$O:$O,A43) -> 0
A44: Đang làm | B44: =COUNTIF('Bug List'!$O:$O,A44) -> 2
A45: Đã sửa | B45: =COUNTIF('Bug List'!$O:$O,A45) -> 79
A46: Không sửa | B46: =COUNTIF('Bug List'!$O:$O,A46) -> 0
A48: Bảng này do scripts/add-bug.py dựng lại từ cột H mỗi lần thêm lỗi.

Sheet Checklist rà soát
A1: Hạng mục | B1: Câu hỏi trước khi merge / phát hành
A2: Giới hạn nền tảng | B2: Tác vụ CPU nặng trong Worker (crypto, JSON lớn, chuỗi truy vấn D1)? Client xử lý phản hồi HTML/1102/5xx?
A3: Engine cũ | B3: Quét API/CSS mới trong public/ và android/.../assets; mục tiêu Chromium 83 + iOS 15 (danh sách trong tests/platform-guards.test.mjs).
A4: Render | B4: render() gọi từ timer, sự kiện nền hoặc khi dữ liệu tải xong có xóa input (mọi ô, không chỉ ô đang focus) hoặc reset luồng đang chạy không? E2E có bước gõ trong lúc API trả lời chậm (window.__slow) không?
A5: Payload một phần | B5: Render có chịu được phản hồi thiếu trường (POST ≠ GET)?
A6: Origin/CORS | B6: WebView SUNMI gửi file://; trình duyệt gửi origin thật; app Android có thể gửi null.
A7: Validate | B7: Mỗi quy tắc dữ liệu một nguồn duy nhất + test đối chiếu client/server.
A8: Fallback im lặng | B8: Tính năng tự chuyển sang cách khác có log và hiện trạng thái không?
A9: Test vs production | B9: Có chạy dưới giới hạn CPU, WebView cũ, thiết bị/emulator thật không?
A10: Android | B10: Luồng nào mất trạng thái khi app bị kill?
A11: Rate limit | B11: Nơi nào khách cả quán dùng chung một IP?
A12: Cách ly quán (SaaS) | B12: Secret, token, cookie, tên DO/KV, cache, file tĩnh, migration có mang dữ liệu/phạm vi của quán khác không?
... A21: Phân quyền dữ liệu | B21: Mỗi vai trò được thấy trường nào? Server có lọc (không chỉ giao diện ẩn) và có test quét phản hồi không lộ tiền, SĐT, khách hàng không?
